betterbasequals/__init__.py
betterbasequals/__main__.py
betterbasequals/bam_adjusters.py
betterbasequals/cli.py
betterbasequals/filter_calls.py
betterbasequals/get_good_bad_kmers.py
betterbasequals/kmerpapa_utils.py
betterbasequals/model_validators.py
betterbasequals/pilup_handlers.py
betterbasequals/quality_utils.py
betterbasequals/somatic_callers.py
betterbasequals/utils.py
betterbasequals-0.3.0.dist-info/LICENSE
betterbasequals-0.3.0.dist-info/METADATA
betterbasequals-0.3.0.dist-info/WHEEL
betterbasequals-0.3.0.dist-info/entry_points.txt
betterbasequals-0.3.0.dist-info/RECORD
