Metadata-Version: 2.1
Name: betterbasequals
Version: 0.3.0
Summary: SNV variant caller that uses discordant overlapping read pairs to calculate sample-specific base error rates.
Home-page: https://github.com/besenbacher/BetterBaseQuals
License: MIT
Author: Søren Besenbacher
Author-email: besenbacher@clin.au.dk
Requires-Python: >=3.8,<3.11
Classifier: License :: OSI Approved :: MIT License
Classifier: Programming Language :: Python :: 3
Classifier: Programming Language :: Python :: 3.8
Classifier: Programming Language :: Python :: 3.9
Classifier: Programming Language :: Python :: 3.10
Requires-Dist: jinja2 (>=3.1.4,<4.0.0)
Requires-Dist: kmerpapa (>=0.2.4,<0.3.0)
Requires-Dist: pandas (>=2.1.3,<3.0.0) ; python_version >= "3.9" and python_version < "3.11"
Requires-Dist: py2bit (>=0.3.0,<0.4.0)
Requires-Dist: pysam (>=0.19.1,<0.20.0)
Project-URL: Repository, https://github.com/besenbacher/BetterBaseQuals
